salsa/__init__.py
salsa/absorber_extractor.py
salsa/absorber_plotter.py
salsa/collect_features.py
salsa/generate_catalog.py
salsa/generate_light_rays.py
salsa/utils/__init__.py
salsa/utils/collect_files.py
salsa/utils/defaults.py
salsa/utils/functions.py
astro_salsa-1.0.0.dist-info/LICENSE
astro_salsa-1.0.0.dist-info/METADATA
astro_salsa-1.0.0.dist-info/WHEEL
astro_salsa-1.0.0.dist-info/top_level.txt
astro_salsa-1.0.0.dist-info/RECORD
