Metadata-Version: 2.1
Name: astro-salsa
Version: 1.0.0
Summary: Synthetic absorber catalog generator from astrophysical simulations
Home-page: https://github.com/biboyd/SALSA
Author: Brendan Boyd
Author-email: boyd.brendan@stonybrook.edu
License: BSD 3-Clause
Keywords: simulation,spectra,astronomy,astrophysics
Platform: UNKNOWN
Classifier: Programming Language :: Python :: 3
Requires-Dist: numpy
Requires-Dist: yt
Requires-Dist: trident
Requires-Dist: spectacle
Requires-Dist: matplotlib
Requires-Dist: pandas
Requires-Dist: scipy
Requires-Dist: mpi4py
